README.md
setup.py
hawksoft/__init__.py
hawksoft/trafficLights.py
hawksoft/trafficLightsOnline.py
hawksoft.trafficLights.egg-info/PKG-INFO
hawksoft.trafficLights.egg-info/SOURCES.txt
hawksoft.trafficLights.egg-info/dependency_links.txt
hawksoft.trafficLights.egg-info/entry_points.txt
hawksoft.trafficLights.egg-info/requires.txt
hawksoft.trafficLights.egg-info/top_level.txt