Metadata-Version: 2.1
Name: hawksoft.trafficLights
Version: 1.0.0
Summary: Knowledge base using pyknow for controlling traffic lights
Home-page: https://gitee.com/xingyongkang/trafficLights
Author: xingyongkang
Author-email: xingyongkang@cqu.edu.cn
License: MIT
Keywords: pyknow,traffic lights,production system
Platform: any
